odoo/addons/pos_product_mergeable_line/README.rst
odoo/addons/pos_product_mergeable_line/__init__.py
odoo/addons/pos_product_mergeable_line/__manifest__.py
odoo/addons/pos_product_mergeable_line/i18n/es.po
odoo/addons/pos_product_mergeable_line/i18n/fr.po
odoo/addons/pos_product_mergeable_line/i18n/it.po
odoo/addons/pos_product_mergeable_line/i18n/pos_product_mergeable_line.pot
odoo/addons/pos_product_mergeable_line/models/__init__.py
odoo/addons/pos_product_mergeable_line/models/pos_session.py
odoo/addons/pos_product_mergeable_line/models/product_template.py
odoo/addons/pos_product_mergeable_line/readme/CONFIGURE.rst
odoo/addons/pos_product_mergeable_line/readme/CONTRIBUTORS.rst
odoo/addons/pos_product_mergeable_line/readme/DESCRIPTION.rst
odoo/addons/pos_product_mergeable_line/static/description/icon.png
odoo/addons/pos_product_mergeable_line/static/description/index.html
odoo/addons/pos_product_mergeable_line/static/description/product_form.png
odoo/addons/pos_product_mergeable_line/static/src/js/models.js
odoo/addons/pos_product_mergeable_line/views/view_product_template.xml
odoo_addon_pos_product_mergeable_line-16.0.1.0.0.6.dist-info/METADATA
odoo_addon_pos_product_mergeable_line-16.0.1.0.0.6.dist-info/WHEEL
odoo_addon_pos_product_mergeable_line-16.0.1.0.0.6.dist-info/top_level.txt
odoo_addon_pos_product_mergeable_line-16.0.1.0.0.6.dist-info/RECORD
